pylifxtiles/__init__.py
pylifxtiles/actions.py
pylifxtiles/alphanum.py
pylifxtiles/colors.py
pylifxtiles/objects.py
pylifxtiles/tiles.py
pylifxtiles-0.1.9.dist-info/LICENSE
pylifxtiles-0.1.9.dist-info/METADATA
pylifxtiles-0.1.9.dist-info/WHEEL
pylifxtiles-0.1.9.dist-info/entry_points.txt
pylifxtiles-0.1.9.dist-info/top_level.txt
pylifxtiles-0.1.9.dist-info/RECORD
