Metadata-Version: 2.1
Name: pylifxtiles
Version: 0.1.9
Summary: Python binding for LIFX Tiles
Home-page: https://github.com/netmanchris/pylifxtiles
Author: netmanchris
Author-email: python@homekitgeek.com
License: Apache2
Keywords: lifx,tiles,api,python
Classifier: Development Status :: 3 - Alpha
Classifier: Intended Audience :: Developers
Classifier: Intended Audience :: System Administrators
Classifier: License :: OSI Approved :: Apache Software License
Classifier: Programming Language :: Python
Classifier: Natural Language :: English
Classifier: Operating System :: OS Independent
Classifier: Topic :: Software Development :: Libraries :: Python Modules
License-File: LICENSE
Requires-Dist: requests
Requires-Dist: lifxlan
Requires-Dist: bitstring (==3.1.9)
Requires-Dist: nose
Requires-Dist: matplotlib
Requires-Dist: Pillow
Provides-Extra: dev
Requires-Dist: check-manifest ; extra == 'dev'
Provides-Extra: test
Requires-Dist: coverage ; extra == 'test'
